fipradio.py
fipradio-1.1.data/scripts/fip
fipradio-1.1.dist-info/DESCRIPTION.rst
fipradio-1.1.dist-info/METADATA
fipradio-1.1.dist-info/RECORD
fipradio-1.1.dist-info/WHEEL
fipradio-1.1.dist-info/metadata.json
fipradio-1.1.dist-info/top_level.txt
