Metadata-Version: 2.0
Name: fipradio
Version: 1.1
Summary: Command line tool to start & stop the stream and mute unwanted songs from FIP radio
Home-page: https://github.com/zopieux/fipradio
Author: Alexandre Macabies
Author-email: UNKNOWN
License: MIT
Platform: UNKNOWN
Classifier: Topic :: Multimedia :: Sound/Audio :: Players
Classifier: Environment :: Console
Classifier: Development Status :: 4 - Beta
Classifier: License :: OSI Approved :: MIT License
Classifier: Programming Language :: Python :: 3
Classifier: Programming Language :: Python :: 3 :: Only
Requires-Dist: aiohttp
